jskiner/cmd.py
jskiner/reduce.py
jskiner/__init__.py
jskiner/jsonl.py
jskiner/jskiner.cpython-38-darwin.so
jskiner/schema.py
jskiner/folder/batch.py
jskiner/folder/__init__.py
jskiner/folder/filter.py
jskiner/folder/main.py
jskiner-0.1.1.dist-info/RECORD
jskiner-0.1.1.dist-info/WHEEL
jskiner-0.1.1.dist-info/entry_points.txt
jskiner-0.1.1.dist-info/METADATA
jskiner-0.1.1.dist-info/license_files/LICENSE
